setup.py
rdistributions/Binomialdistribution.py
rdistributions/Gaussiandistribution.py
rdistributions/Genericdistribution.py
rdistributions/__init__.py
rdistributions.egg-info/PKG-INFO
rdistributions.egg-info/SOURCES.txt
rdistributions.egg-info/dependency_links.txt
rdistributions.egg-info/not-zip-safe
rdistributions.egg-info/top_level.txt